mlscholar/__init__.py
mlscholar/frontend/.DS_Store
mlscholar/frontend/.streamlit/config.toml
mlscholar/frontend/Home.py
mlscholar/frontend/__init__.py
mlscholar/frontend/assets/geo-sps.png
mlscholar/frontend/assets/logo-openpm.png
mlscholar/frontend/contents/__init__.py
mlscholar/frontend/contents/dataUI.py
mlscholar/frontend/pages/1_Search.py
mlscholar/frontend/pages/2_Use.py
mlscholar/frontend/pages/3_Build.py
mlscholar/frontend/pages/__init__.py
mlscholar-0.0.0.dist-info/METADATA
mlscholar-0.0.0.dist-info/WHEEL
mlscholar-0.0.0.dist-info/RECORD
