Metadata-Version: 2.1
Name: mlscholar
Version: 0.0.0
Summary: Search, explore and use ML models...
Author: altar31
Author-email: damien.sicard31@gmail.com
Requires-Python: >=3.11,<4.0
Classifier: Programming Language :: Python :: 3
Classifier: Programming Language :: Python :: 3.11
Requires-Dist: huggingface-hub (>=0.16.4,<0.17.0)
Requires-Dist: scikit-learn (>=1.3.0,<2.0.0)
Requires-Dist: streamlit (>=1.25.0,<2.0.0)
Requires-Dist: streamlit-aggrid (>=0.3.4.post3,<0.4.0)
